rero_invenio_base/__init__.py
rero_invenio_base/cli/__init__.py
rero_invenio_base/cli/es/__init__.py
rero_invenio_base/cli/es/alias.py
rero_invenio_base/cli/es/index.py
rero_invenio_base/cli/es/slm/__init__.py
rero_invenio_base/cli/es/slm/cli.py
rero_invenio_base/cli/es/snapshot/__init__.py
rero_invenio_base/cli/es/snapshot/cli.py
rero_invenio_base/cli/es/snapshot/repository.py
rero_invenio_base/cli/es/task.py
rero_invenio_base/cli/shared.py
rero_invenio_base/cli/utils.py
rero_invenio_base/config.py
rero_invenio_base/ext.py
rero_invenio_base/modules/__init__.py
rero_invenio_base/modules/export/__init__.py
rero_invenio_base/modules/export/config.py
rero_invenio_base/modules/export/ext.py
rero_invenio_base/modules/export/proxies.py
rero_invenio_base/modules/export/views.py
rero_invenio_base/modules/tasks.py
rero_invenio_base/modules/utils.py
rero_invenio_base/version.py
rero_invenio_base-0.3.3.dist-info/licenses/LICENSE
rero_invenio_base-0.3.3.dist-info/WHEEL
rero_invenio_base-0.3.3.dist-info/entry_points.txt
rero_invenio_base-0.3.3.dist-info/METADATA
rero_invenio_base-0.3.3.dist-info/RECORD
