Metadata-Version: 2.4
Name: rero-invenio-base
Version: 0.3.3
Summary: Generic backend libraries for RERO Invenio instances.
Author: RERO
Author-email: RERO <software@rero.ch>
License-Expression: AGPL-3.0
License-File: LICENSE
Requires-Dist: pyyaml<=7.0
Requires-Dist: jsonpatch<=2.0
Requires-Dist: mako>=1.2.2
Requires-Dist: dparse>=0.5.2
Requires-Dist: invenio-search[elasticsearch7]>=2.1.0
Requires-Dist: invenio-db[postgresql]>=1.1.0
Requires-Dist: invenio-indexer>=2.2.0
Requires-Dist: invenio-records-rest>=2.2.0
Requires-Dist: sqlalchemy>=1.3.0
Requires-Dist: poethepoet>=0.36.0
Requires-Python: >=3.9, <3.13
